{
    "setting": {},
    "condition": {
        "plugin": {
            "list": []
        },
        "game": {
            "list": []
        },
        "gamePlugin": {
            "list": []
        },
        "miniprogram": {
            "list": [
                {
                    "id": -1,
                    "name": "db guide",
                    "pathName": "pages/databaseGuide/databaseGuide",
                    "query": ""
                },
                {
                    "name": "pages/register/register",
                    "pathName": "pages/register/register",
                    "query": "",
                    "scene": null
                },
                {
                    "name": "pages/canteenSelection/canteenSelection",
                    "pathName": "pages/canteenSelection/canteenSelection",
                    "query": "",
                    "scene": null
                },
                {
                    "name": "pages/az/az",
                    "pathName": "pages/az/az",
                    "query": "",
                    "scene": null
                },
                {
                    "name": "pages/foodSelection/foodSelection",
                    "pathName": "pages/foodSelection/foodSelection",
                    "query": "",
                    "scene": null
                },
                {
                    "name": "pages/studentConsole/studentConsole",
                    "pathName": "pages/studentConsole/studentConsole",
                    "query": "",
                    "scene": null
                },
                {
                    "name": "pages/teacherConsole/teacherConsole",
                    "pathName": "pages/teacherConsole/teacherConsole",
                    "query": "",
                    "scene": null
                },
                {
                    "name": "pages/canteenManagerConsole/canteenManagerConsole",
                    "pathName": "pages/canteenManagerConsole/canteenManagerConsole",
                    "query": "",
                    "scene": null
                },
                {
                    "name": "pages/uploadDishes/uploadDishes",
                    "pathName": "pages/uploadDishes/uploadDishes",
                    "query": "",
                    "scene": null
                },
                {
                    "name": "pages/infoInput/infoInput",
                    "pathName": "pages/infoInput/infoInput",
                    "query": "",
                    "scene": null
                },
                {
                    "name": "pages/studentHistoryOrder/studentHistoryOrder",
                    "pathName": "pages/studentHistoryOrder/studentHistoryOrder",
                    "query": "",
                    "scene": null
                }
            ]
        }
    }
}